AUTHORS.rst
CONTRIBUTING.rst
LICENSE
MANIFEST.in
README.rst
requirements.txt
setup.py
dbexample/__init__.py
dbexample/example.py
dbexample.egg-info/PKG-INFO
dbexample.egg-info/SOURCES.txt
dbexample.egg-info/dependency_links.txt
dbexample.egg-info/entry_points.txt
dbexample.egg-info/top_level.txt
dbexample/data/546d39a0-5bf2-47ad-8ac9-0a7d85eaa74d.msgpack
dbexample/data/9d320500-b3c8-47a2-8554-ca63fa092c17.msgpack
dbexample/data/a3e64b70-c5b9-4437-80ea-ea6a7198d397.msgpack
dbexample/data/d5e02ae2-33fe-444e-80e6-e65ba4cce556.msgpack
dbexample/data/de526f6a-29ed-4369-a0d8-c5bf50164e14.msgpack
dbexample/data/e1ff3825-eac2-41f5-abd9-d04d9373e5de.msgpack
dbexample/tests/__init__.py
dbexample/tests/conftest.py
dbexample/tests/test_example.py
docs/Makefile
docs/make.bat
docs/source/changelog.rst
docs/source/conf.py
docs/source/index.rst
docs/source/installation.rst
docs/source/min_versions.rst
docs/source/usage.rst