Metadata-Version: 1.2
Name: dbexample
Version: 0.2.1
Summary: An example nsls-ii database that can be accessed by the databroker.
Home-page: https://github.com/st3107/dbexample
Author: Songsheng Tao
Author-email: st3107@columbia.edu
License: BSD (3-clause)
Platform: UNKNOWN
Classifier: Development Status :: 2 - Pre-Alpha
Classifier: Natural Language :: English
Classifier: Programming Language :: Python :: 3
Requires-Python: >=3.7
